README.rst
setup.py
korbit/__init__.py
korbit/api.py
korbit/models.py
korbit.egg-info/PKG-INFO
korbit.egg-info/SOURCES.txt
korbit.egg-info/dependency_links.txt
korbit.egg-info/requires.txt
korbit.egg-info/top_level.txt
tests/__init__.py
tests/basic_test.py
tests/model_test.py