Metadata-Version: 1.0
Name: korbit
Version: 0.1.4
Summary: A Python wrapper for Korbit API
Home-page: http://github.com/suminb/korbit
Author: Sumin Byeon
Author-email: suminb@gmail.com
License: UNKNOWN
Platform: UNKNOWN
